Workbook
Name Slicer_Processing_Status: #N/A
Name Slicer_Security_Name: #N/A

Sheet Dashboard
A2: Treasury Funding & Settlement Terminal
E4: =Pivot_Data!I1 -> Sum of Net Payout | H4: Total TDS Withheld: | L4: Total Bonus Shares:
E5: =Pivot_Data!I2 -> 36135 | H5: =Pivot_Data!J2 -> 4015 | L5: =Pivot_Data!K2 -> 0

Sheet Ledger
A1: Client ID | B1: Security Name | C1: Trade Date | D1: Settled Shares | E1: Dividend Rate | F1: Gross Entitlement | G1: TDS Withheld (10%) | H1: Net Payout | I1: Bonus Shares Received | J1: Whole Bonus Shares | K1: Fractional Shares | L1: Cash-in-Lieu Payout | M1: Adjusted Total Cash Payout | N1: New Total Shares | O1: Processing Status
A2: ACC-IND-10002 | B2: TRANSCOR | C2: 43930 | D2: 7800 | E2: =SUMIFS(CA_Feed!F:F, CA_Feed!B:B, B2, CA_Feed!E:E, "*DIVIDEND*", CA_Feed!D:D, ">="&C2) -> 1.5 | F2: =D2 * E2 -> 11700 | G2: =F2 * 0.1 -> 1170 | H2: =F2 - G2 -> 10530 | I2: =D2 * SUMIFS(CA_Feed!G:G, CA_Feed!B:B, B2, CA_Feed!E:E, "*BONUS*", CA_Feed!D:D, ">="&C2) -> 0 | J2: =INT(I2) -> 0 | K2: =I2-J2 -> 0 | L2: =IF(K2>0, K2 * VLOOKUP(B2, CA_Feed!B:N, 13, FALSE), 0) -> 0 | M2: =H2 + L2 -> 10530 | N2: =IF(J2>0,D2 +J2,0) -> 0 | O2: =IF(COUNTIFS(CA_Feed!B:B, B2)=0, "No Action Announced", IF(COUNTIFS(CA_Feed!B:B, B2, CA_Feed!D:D, ">="&C2)>0, "Processed (Eligible)", "Ineligible (Post Ex-Date)")) -> Processed (Eligible)
A3: ACC-IND-10004 | B3: TRANSCOR | C3: 43459 | D3: 650 | E3: =SUMIFS(CA_Feed!F:F, CA_Feed!B:B, B3, CA_Feed!E:E, "*DIVIDEND*", CA_Feed!D:D, ">="&C3) -> 1.5 | F3: =D3 * E3 -> 975 | G3: =F3 * 0.1 -> 97.5 | H3: =F3 - G3 -> 877.5 | I3: =D3 * SUMIFS(CA_Feed!G:G, CA_Feed!B:B, B3, CA_Feed!E:E, "*BONUS*", CA_Feed!D:D, ">="&C3) -> 0 | J3: =INT(I3) -> 0 | K3: =I3-J3 -> 0 | L3: =IF(K3>0, K3 * VLOOKUP(B3, CA_Feed!B:N, 13, FALSE), 0) -> 0 | M3: =H3 + L3 -> 877.5 | N3: =IF(J3>0,D3 +J3,0) -> 0 | O3: =IF(COUNTIFS(CA_Feed!B:B, B3)=0, "No Action Announced", IF(COUNTIFS(CA_Feed!B:B, B3, CA_Feed!D:D, ">="&C3)>0, "Processed (Eligible)", "Ineligible (Post Ex-Date)")) -> Processed (Eligible)
A4: ACC-IND-10005 | B4: SUMEDHA | C4: 44106 | D4: 6000 | E4: =SUMIFS(CA_Feed!F:F, CA_Feed!B:B, B4, CA_Feed!E:E, "*DIVIDEND*", CA_Feed!D:D, ">="&C4) -> 3 | F4: =D4 * E4 -> 18000 | G4: =F4 * 0.1 -> 1800 | H4: =F4 - G4 -> 16200 | I4: =D4 * SUMIFS(CA_Feed!G:G, CA_Feed!B:B, B4, CA_Feed!E:E, "*BONUS*", CA_Feed!D:D, ">="&C4) -> 0 | J4: =INT(I4) -> 0 | K4: =I4-J4 -> 0 | L4: =IF(K4>0, K4 * VLOOKUP(B4, CA_Feed!B:N, 13, FALSE), 0) -> 0 | M4: =H4 + L4 -> 16200 | N4: =IF(J4>0,D4 +J4,0) -> 0 | O4: =IF(COUNTIFS(CA_Feed!B:B, B4)=0, "No Action Announced", IF(COUNTIFS(CA_Feed!B:B, B4, CA_Feed!D:D, ">="&C4)>0, "Processed (Eligible)", "Ineligible (Post Ex-Date)")) -> Processed (Eligible)
A5: ACC-IND-10007 | B5: EENTER | C5: 44191 | D5: 2350 | E5: =SUMIFS(CA_Feed!F:F, CA_Feed!B:B, B5, CA_Feed!E:E, "*DIVIDEND*", CA_Feed!D:D, ">="&C5) -> 3 | F5: =D5 * E5 -> 7050 | G5: =F5 * 0.1 -> 705 | H5: =F5 - G5 -> 6345 | I5: =D5 * SUMIFS(CA_Feed!G:G, CA_Feed!B:B, B5, CA_Feed!E:E, "*BONUS*", CA_Feed!D:D, ">="&C5) -> 0 | J5: =INT(I5) -> 0 | K5: =I5-J5 -> 0 | L5: =IF(K5>0, K5 * VLOOKUP(B5, CA_Feed!B:N, 13, FALSE), 0) -> 0 | M5: =H5 + L5 -> 6345 | N5: =IF(J5>0,D5 +J5,0) -> 0 | O5: =IF(COUNTIFS(CA_Feed!B:B, B5)=0, "No Action Announced", IF(COUNTIFS(CA_Feed!B:B, B5, CA_Feed!D:D, ">="&C5)>0, "Processed (Eligible)", "Ineligible (Post Ex-Date)")) -> Processed (Eligible)
A6: ACC-IND-10008 | B6: PRITHVIEXCH | C6: 42919 | D6: 10050 | E6: =SUMIFS(CA_Feed!F:F, CA_Feed!B:B, B6, CA_Feed!E:E, "*DIVIDEND*", CA_Feed!D:D, ">="&C6) -> 6.5 | F6: =D6 * E6 -> 65325 | G6: =F6 * 0.1 -> 6532.5 | H6: =F6 - G6 -> 58792.5 | I6: =D6 * SUMIFS(CA_Feed!G:G, CA_Feed!B:B, B6, CA_Feed!E:E, "*BONUS*", CA_Feed!D:D, ">="&C6) -> 0 | J6: =INT(I6) -> 0 | K6: =I6-J6 -> 0 | L6: =IF(K6>0, K6 * VLOOKUP(B6, CA_Feed!B:N, 13, FALSE), 0) -> 0 | M6: =H6 + L6 -> 58792.5 | N6: =IF(J6>0,D6 +J6,0) -> 0 | O6: =IF(COUNTIFS(CA_Feed!B:B, B6)=0, "No Action Announced", IF(COUNTIFS(CA_Feed!B:B, B6, CA_Feed!D:D, ">="&C6)>0, "Processed (Eligible)", "Ineligible (Post Ex-Date)")) -> Processed (Eligible)
A7: ACC-IND-10010 | B7: TRANSCOR | C7: 42864 | D7: 9550 | E7: =SUMIFS(CA_Feed!F:F, CA_Feed!B:B, B7, CA_Feed!E:E, "*DIVIDEND*", CA_Feed!D:D, ">="&C7) -> 1.5 | F7: =D7 * E7 -> 14325 | G7: =F7 * 0.1 -> 1432.5 | H7: =F7 - G7 -> 12892.5 | I7: =D7 * SUMIFS(CA_Feed!G:G, CA_Feed!B:B, B7, CA_Feed!E:E, "*BONUS*", CA_Feed!D:D, ">="&C7) -> 0 | J7: =INT(I7) -> 0 | K7: =I7-J7 -> 0 | L7: =IF(K7>0, K7 * VLOOKUP(B7, CA_Feed!B:N, 13, FALSE), 0) -> 0 | M7: =H7 + L7 -> 12892.5 | N7: =IF(J7>0,D7 +J7,0) -> 0 | O7: =IF(COUNTIFS(CA_Feed!B:B, B7)=0, "No Action Announced", IF(COUNTIFS(CA_Feed!B:B, B7, CA_Feed!D:D, ">="&C7)>0, "Processed (Eligible)", "Ineligible (Post Ex-Date)")) -> Processed (Eligible)
A8: ACC-IND-10500 | B8: CRISIL | C8: 44252 | D8: 80 | E8: =SUMIFS(CA_Feed!F:F, CA_Feed!B:B, B8, CA_Feed!E:E, "*DIVIDEND*", CA_Feed!D:D, ">="&C8) -> 19 | F8: =D8 * E8 -> 1520 | G8: =F8 * 0.1 -> 152 | H8: =F8 - G8 -> 1368 | I8: =D8 * SUMIFS(CA_Feed!G:G, CA_Feed!B:B, B8, CA_Feed!E:E, "*BONUS*", CA_Feed!D:D, ">="&C8) -> 0 | J8: =INT(I8) -> 0 | K8: =I8-J8 -> 0 | L8: =IF(K8>0, K8 * VLOOKUP(B8, CA_Feed!B:N, 13, FALSE), 0) -> 0 | M8: =H8 + L8 -> 1368 | N8: =IF(J8>0,D8 +J8,0) -> 0 | O8: =IF(COUNTIFS(CA_Feed!B:B, B8)=0, "No Action Announced", IF(COUNTIFS(CA_Feed!B:B, B8, CA_Feed!D:D, ">="&C8)>0, "Processed (Eligible)", "Ineligible (Post Ex-Date)")) -> Processed (Eligible)
A9: ACC-IND-10012 | B9: SUMEDHA | C9: 44669 | D9: 2150 | E9: =SUMIFS(CA_Feed!F:F, CA_Feed!B:B, B9, CA_Feed!E:E, "*DIVIDEND*", CA_Feed!D:D, ">="&C9) -> 3 | F9: =D9 * E9 -> 6450 | G9: =F9 * 0.1 -> 645 | H9: =F9 - G9 -> 5805 | I9: =D9 * SUMIFS(CA_Feed!G:G, CA_Feed!B:B, B9, CA_Feed!E:E, "*BONUS*", CA_Feed!D:D, ">="&C9) -> 0 | J9: =INT(I9) -> 0 | K9: =I9-J9 -> 0 | L9: =IF(K9>0, K9 * VLOOKUP(B9, CA_Feed!B:N, 13, FALSE), 0) -> 0 | M9: =H9 + L9 -> 5805 | N9: =IF(J9>0,D9 +J9,0) -> 0 | O9: =IF(COUNTIFS(CA_Feed!B:B, B9)=0, "No Action Announced", IF(COUNTIFS(CA_Feed!B:B, B9, CA_Feed!D:D, ">="&C9)>0, "Processed (Eligible)", "Ineligible (Post Ex-Date)")) -> Processed (Eligible)
A10: ACC-IND-10013 | B10: BHARAT | C10: 42181 | D10: 2700 | E10: =SUMIFS(CA_Feed!F:F, CA_Feed!B:B, B10, CA_Feed!E:E, "*DIVIDEND*", CA_Feed!D:D, ">="&C10) -> 1.2 | F10: =D10 * E10 -> 3240 | G10: =F10 * 0.1 -> 324 | H10: =F10 - G10 -> 2916 | I10: =D10 * SUMIFS(CA_Feed!G:G, CA_Feed!B:B, B10, CA_Feed!E:E, "*BONUS*", CA_Feed!D:D, ">="&C10) -> 0 | J10: =INT(I10) -> 0 | K10: =I10-J10 -> 0 | L10: =IF(K10>0, K10 * VLOOKUP(B10, CA_Feed!B:N, 13, FALSE), 0) -> 0 | M10: =H10 + L10 -> 2916 | N10: =IF(J10>0,D10 +J10,0) -> 0 | O10: =IF(COUNTIFS(CA_Feed!B:B, B10)=0, "No Action Announced", IF(COUNTIFS(CA_Feed!B:B, B10, CA_Feed!D:D, ">="&C10)>0, "Processed (Eligible)", "Ineligible (Post Ex-Date)")) -> Processed (Eligible)
A11: ACC-IND-10014 | B11: BHARAT | C11: 43087 | D11: 6350 | E11: =SUMIFS(CA_Feed!F:F, CA_Feed!B:B, B11, CA_Feed!E:E, "*DIVIDEND*", CA_Feed!D:D, ">="&C11) -> 1.2 | F11: =D11 * E11 -> 7620 | G11: =F11 * 0.1 -> 762 | H11: =F11 - G11 -> 6858 | I11: =D11 * SUMIFS(CA_Feed!G:G, CA_Feed!B:B, B11, CA_Feed!E:E, "*BONUS*", CA_Feed!D:D, ">="&C11) -> 0 | J11: =INT(I11) -> 0 | K11: =I11-J11 -> 0 | L11: =IF(K11>0, K11 * VLOOKUP(B11, CA_Feed!B:N, 13, FALSE), 0) -> 0 | M11: =H11 + L11 -> 6858 | N11: =IF(J11>0,D11 +J11,0) -> 0 | O11: =IF(COUNTIFS(CA_Feed!B:B, B11)=0, "No Action Announced", IF(COUNTIFS(CA_Feed!B:B, B11, CA_Feed!D:D, ">="&C11)>0, "Processed (Eligible)", "Ineligible (Post Ex-Date)")) -> Processed (Eligible)
A12: ACC-IND-10090 | B12: CRISIL | C12: 43947 | D12: 80 | E12: =SUMIFS(CA_Feed!F:F, CA_Feed!B:B, B12, CA_Feed!E:E, "*DIVIDEND*", CA_Feed!D:D, ">="&C12) -> 19 | F12: =D12 * E12 -> 1520 | G12: =F12 * 0.1 -> 152 | H12: =F12 - G12 -> 1368 | I12: =D12 * SUMIFS(CA_Feed!G:G, CA_Feed!B:B, B12, CA_Feed!E:E, "*BONUS*", CA_Feed!D:D, ">="&C12) -> 0 | J12: =INT(I12) -> 0 | K12: =I12-J12 -> 0 | L12: =IF(K12>0, K12 * VLOOKUP(B12, CA_Feed!B:N, 13, FALSE), 0) -> 0 | M12: =H12 + L12 -> 1368 | N12: =IF(J12>0,D12 +J12,0) -> 0 | O12: =IF(COUNTIFS(CA_Feed!B:B, B12)=0, "No Action Announced", IF(COUNTIFS(CA_Feed!B:B, B12, CA_Feed!D:D, ">="&C12)>0, "Processed (Eligible)", "Ineligible (Post Ex-Date)")) -> Processed (Eligible)
A13: ACC-IND-10018 | B13: PRITHVIEXCH | C13: 42135 | D13: 4950 | E13: =SUMIFS(CA_Feed!F:F, CA_Feed!B:B, B13, CA_Feed!E:E, "*DIVIDEND*", CA_Feed!D:D, ">="&C13) -> 6.5 | F13: =D13 * E13 -> 32175 | G13: =F13 * 0.1 -> 3217.5 | H13: =F13 - G13 -> 28957.5 | I13: =D13 * SUMIFS(CA_Feed!G:G, CA_Feed!B:B, B13, CA_Feed!E:E, "*BONUS*", CA_Feed!D:D, ">="&C13) -> 0 | J13: =INT(I13) -> 0 | K13: =I13-J13 -> 0 | L13: =IF(K13>0, K13 * VLOOKUP(B13, CA_Feed!B:N, 13, FALSE), 0) -> 0 | M13: =H13 + L13 -> 28957.5 | N13: =IF(J13>0,D13 +J13,0) -> 0 | O13: =IF(COUNTIFS(CA_Feed!B:B, B13)=0, "No Action Announced", IF(COUNTIFS(CA_Feed!B:B, B13, CA_Feed!D:D, ">="&C13)>0, "Processed (Eligible)", "Ineligible (Post Ex-Date)")) -> Processed (Eligible)
... A765: ACC-IND-10638 | B765: CRISIL | C765: 42438 | D765: 15 | E765: =SUMIFS(CA_Feed!F:F, CA_Feed!B:B, B765, CA_Feed!E:E, "*DIVIDEND*", CA_Feed!D:D, ">="&C765) -> 19 | F765: =D765 * E765 -> 285 | G765: =F765 * 0.1 -> 28.5 | H765: =F765 - G765 -> 256.5 | I765: =D765 * SUMIFS(CA_Feed!G:G, CA_Feed!B:B, B765, CA_Feed!E:E, "*BONUS*", CA_Feed!D:D, ">="&C765) -> 0 | J765: =INT(I765) -> 0 | K765: =I765-J765 -> 0 | L765: =IF(K765>0, K765 * VLOOKUP(B765, CA_Feed!B:N, 13, FALSE), 0) -> 0 | M765: =H765 + L765 -> 256.5 | N765: =IF(J765>0,D765 +J765,0) -> 0 | O765: =IF(COUNTIFS(CA_Feed!B:B, B765)=0, "No Action Announced", IF(COUNTIFS(CA_Feed!B:B, B765, CA_Feed!D:D, ">="&C765)>0, "Processed (Eligible)", "Ineligible (Post Ex-Date)")) -> Processed (Eligible)

Sheet CA_Feed
A1: Security Code | B1: Security Name | C1: Company Name | D1: Ex Date | E1: Purpose | F1: Amount in Rupees | G1: Bonus Multiplier | H1: Record Date | I1: BC Start Date | J1: BC End Date | K1: ND Start Date | L1: ND End Date | M1: Actual Payment Date | N1: Fractional Settlement Price
A2: 531688 | B2: PRITHVIEXCH | C2: Prithvi Exchange (India) Ltd | D2: 46253 | E2: Final Dividend | F2: 0.5 | G2: =IF(ISNUMBER(SEARCH("BONUS", E2)), VALUE(LEFT(F2, FIND(":", F2)-1)) / VALUE(MID(F2, FIND(":", F2)+1, 10)), 0) -> 0 | H2: 46253 | I2: - | J2: - | K2: 46253 | L2: 46253 | M2: -
A3: 531278 | B3: ELIXIR | C3: Elixir Capital Ltd | D3: 46252 | E3: Final Dividend | F3: 1.25 | G3: =IF(ISNUMBER(SEARCH("BONUS", E3)), VALUE(LEFT(F3, FIND(":", F3)-1)) / VALUE(MID(F3, FIND(":", F3)+1, 10)), 0) -> 0 | H3: 46252 | I3: - | J3: - | K3: 46252 | L3: 46252 | M3: -
A4: 532333 | B4: HBPOR | C4: HB Portfolio Ltd | D4: 46248 | E4: Interim Dividend | F4: 1.25 | G4: =IF(ISNUMBER(SEARCH("BONUS", E4)), VALUE(LEFT(F4, FIND(":", F4)-1)) / VALUE(MID(F4, FIND(":", F4)+1, 10)), 0) -> 0 | H4: 46248 | I4: - | J4: - | K4: 46248 | L4: 46248 | M4: -
A5: 530419 | B5: SUMEDHA | C5: Sumedha Fiscal Services Ltd | D5: 46247 | E5: Final Dividend | F5: 1 | G5: =IF(ISNUMBER(SEARCH("BONUS", E5)), VALUE(LEFT(F5, FIND(":", F5)-1)) / VALUE(MID(F5, FIND(":", F5)+1, 10)), 0) -> 0 | H5: 46247 | I5: - | J5: - | K5: 46247 | L5: 46247 | M5: -
A6: 501386 | B6: EENTER | C6: E & E Enterprises Ltd | D6: 46245 | E6: Final Dividend | F6: 1 | G6: =IF(ISNUMBER(SEARCH("BONUS", E6)), VALUE(LEFT(F6, FIND(":", F6)-1)) / VALUE(MID(F6, FIND(":", F6)+1, 10)), 0) -> 0 | H6: 46245 | I6: - | J6: - | K6: 46245 | L6: 46245 | M6: -
A7: 523019 | B7: BNRSEC | C7: BN Rathi Securities Ltd | D7: 46241 | E7: Final Dividend | F7: 0.5 | G7: =IF(ISNUMBER(SEARCH("BONUS", E7)), VALUE(LEFT(F7, FIND(":", F7)-1)) / VALUE(MID(F7, FIND(":", F7)+1, 10)), 0) -> 0 | H7: 46241 | I7: - | J7: - | K7: 46241 | L7: 46241 | M7: -
A8: 508905 | B8: NEXOME | C8: Nexome Capital Markets Ltd | D8: 46234 | E8: Final Dividend | F8: 1.5 | G8: =IF(ISNUMBER(SEARCH("BONUS", E8)), VALUE(LEFT(F8, FIND(":", F8)-1)) / VALUE(MID(F8, FIND(":", F8)+1, 10)), 0) -> 0 | H8: 46234 | I8: - | J8: - | K8: 46234 | L8: 46234 | M8: -
A9: 500092 | B9: CRISIL | C9: Crisil Ltd | D9: 46230 | E9: Interim Dividend | F9: 4 | G9: =IF(ISNUMBER(SEARCH("BONUS", E9)), VALUE(LEFT(F9, FIND(":", F9)-1)) / VALUE(MID(F9, FIND(":", F9)+1, 10)), 0) -> 0 | H9: 46230 | I9: - | J9: - | K9: 46230 | L9: 46230 | M9: -
A10: 532410 | B10: TRANSCOR | C10: Transcorp International Ltd | D10: 46206 | E10: Final Dividend | F10: 0.4 | G10: =IF(ISNUMBER(SEARCH("BONUS", E10)), VALUE(LEFT(F10, FIND(":", F10)-1)) / VALUE(MID(F10, FIND(":", F10)+1, 10)), 0) -> 0 | H10: 46206 | I10: - | J10: - | K10: 46206 | L10: 46206 | M10: -
A11: 500092 | B11: CRISIL | C11: Crisil Ltd | D11: 46135 | E11: Interim Dividend | F11: 5 | G11: =IF(ISNUMBER(SEARCH("BONUS", E11)), VALUE(LEFT(F11, FIND(":", F11)-1)) / VALUE(MID(F11, FIND(":", F11)+1, 10)), 0) -> 0 | H11: 46135 | I11: - | J11: - | K11: 46135 | L11: 46135 | M11: -
A12: 500092 | B12: CRISIL | C12: Crisil Ltd | D12: 46114 | E12: Final Dividend | F12: 10 | G12: =IF(ISNUMBER(SEARCH("BONUS", E12)), VALUE(LEFT(F12, FIND(":", F12)-1)) / VALUE(MID(F12, FIND(":", F12)+1, 10)), 0) -> 0 | H12: 46115 | I12: - | J12: - | K12: 46114 | L12: 46114 | M12: -
A13: 544536 | B13: WEALTH | C13: Wealth First Portfolio Managers Ltd | D13: 46063 | E13: Interim Dividend | F13: 4 | G13: =IF(ISNUMBER(SEARCH("BONUS", E13)), VALUE(LEFT(F13, FIND(":", F13)-1)) / VALUE(MID(F13, FIND(":", F13)+1, 10)), 0) -> 0 | H13: 46063 | I13: - | J13: - | K13: 46063 | L13: 46063 | M13: -
... A40: 534732 | B40: CASPIAN | C40: Caspian Corporate Services Ltd | D40: 45588 | E40: Final Dividend | F40: 0.05 | G40: =IF(ISNUMBER(SEARCH("BONUS", E40)), VALUE(LEFT(F40, FIND(":", F40)-1)) / VALUE(MID(F40, FIND(":", F40)+1, 10)), 0) -> 0 | H40: 45588 | I40: - | J40: - | K40: 45588 | L40: 45588 | M40: -
A41: 538382 | B41: WESTLEIRES | C41: West Leisure Resorts Ltd | D41: 45562 | E41: Final Dividend | F41: 0.1 | G41: =IF(ISNUMBER(SEARCH("BONUS", E41)), VALUE(LEFT(F41, FIND(":", F41)-1)) / VALUE(MID(F41, FIND(":", F41)+1, 10)), 0) -> 0 | H41: 45563 | I41: - | J41: - | K41: - | L41: - | M41: -
A42: 542544 | B42: JYOTIN | C42: Jyot International Marketing Ltd | D42: 45558 | E42: Interim Dividend | F42: 0.05 | G42: =IF(ISNUMBER(SEARCH("BONUS", E42)), VALUE(LEFT(F42, FIND(":", F42)-1)) / VALUE(MID(F42, FIND(":", F42)+1, 10)), 0) -> 0 | H42: 45558 | I42: - | J42: - | K42: - | L42: - | M42: -
A43: 544207 | B43: RELIABLE | C43: Reliable Data Services Ltd | D43: 45555 | E43: Final Dividend | F43: 0.03 | G43: =IF(ISNUMBER(SEARCH("BONUS", E43)), VALUE(LEFT(F43, FIND(":", F43)-1)) / VALUE(MID(F43, FIND(":", F43)+1, 10)), 0) -> 0 | H43: 45555 | I43: - | J43: - | K43: 45551 | L43: 45555 | M43: -
A44: 511501 | B44: BHARAT | C44: Bharat Bhushan Finance & Commodity Brokers Ltd | D44: 45552 | E44: Final Dividend | F44: 0.6 | G44: =IF(ISNUMBER(SEARCH("BONUS", E44)), VALUE(LEFT(F44, FIND(":", F44)-1)) / VALUE(MID(F44, FIND(":", F44)+1, 10)), 0) -> 0 | H44: - | I44: 45553 | J44: 45559 | K44: 45553 | L44: 45553 | M44: -
A45: 534691 | B45: COMCL | C45: Comfort Commotrade Ltd | D45: 45548 | E45: Final Dividend | F45: 0.5 | G45: =IF(ISNUMBER(SEARCH("BONUS", E45)), VALUE(LEFT(F45, FIND(":", F45)-1)) / VALUE(MID(F45, FIND(":", F45)+1, 10)), 0) -> 0 | H45: 45551 | I45: - | J45: - | K45: 45551 | L45: 45551 | M45: -
A46: 500450 | B46: MPILCORPL | C46: MPIL Corporation Ltd | D46: 45548 | E46: Final Dividend | F46: 0.9 | G46: =IF(ISNUMBER(SEARCH("BONUS", E46)), VALUE(LEFT(F46, FIND(":", F46)-1)) / VALUE(MID(F46, FIND(":", F46)+1, 10)), 0) -> 0 | H46: - | I46: 45552 | J46: 45559 | K46: 45551 | L46: 45552 | M46: -
A47: 500189 | B47: NDLVENTURE | C47: NDL Ventures Ltd | D47: 45541 | E47: Final Dividend | F47: 1 | G47: =IF(ISNUMBER(SEARCH("BONUS", E47)), VALUE(LEFT(F47, FIND(":", F47)-1)) / VALUE(MID(F47, FIND(":", F47)+1, 10)), 0) -> 0 | H47: 45541 | I47: - | J47: - | K47: 45537 | L47: 45541 | M47: -
A48: 531688 | B48: PRITHVIEXCH | C48: Prithvi Exchange (India) Ltd | D48: 45540 | E48: Final Dividend | F48: 0.5 | G48: =IF(ISNUMBER(SEARCH("BONUS", E48)), VALUE(LEFT(F48, FIND(":", F48)-1)) / VALUE(MID(F48, FIND(":", F48)+1, 10)), 0) -> 0 | H48: 45540 | I48: - | J48: - | K48: 45534 | L48: 45540 | M48: -
A49: 501386 | B49: EENTER | C49: E & E Enterprises Ltd | D49: 45534 | E49: Final Dividend | F49: 1 | G49: =IF(ISNUMBER(SEARCH("BONUS", E49)), VALUE(LEFT(F49, FIND(":", F49)-1)) / VALUE(MID(F49, FIND(":", F49)+1, 10)), 0) -> 0 | H49: 45534 | I49: - | J49: - | K49: 45534 | L49: 45534 | M49: -
A50: 530419 | B50: SUMEDHA | C50: Sumedha Fiscal Services Ltd | D50: 45525 | E50: Final Dividend | F50: 1 | G50: =IF(ISNUMBER(SEARCH("BONUS", E50)), VALUE(LEFT(F50, FIND(":", F50)-1)) / VALUE(MID(F50, FIND(":", F50)+1, 10)), 0) -> 0 | H50: 45525 | I50: - | J50: - | K50: 45518 | L50: 45525 | M50: -
A51: 531278 | B51: ELIXIR | C51: Elixir Capital Ltd | D51: 45520 | E51: Final Dividend | F51: 1.25 | G51: =IF(ISNUMBER(SEARCH("BONUS", E51)), VALUE(LEFT(F51, FIND(":", F51)-1)) / VALUE(MID(F51, FIND(":", F51)+1, 10)), 0) -> 0 | H51: - | I51: 45523 | J51: 45530 | K51: 45523 | L51: 45523 | M51: -
A52: 532410 | B52: TRANSCOR | C52: Transcorp International Ltd | D52: 45485 | E52: Final Dividend | F52: 0.3 | G52: =IF(ISNUMBER(SEARCH("BONUS", E52)), VALUE(LEFT(F52, FIND(":", F52)-1)) / VALUE(MID(F52, FIND(":", F52)+1, 10)), 0) -> 0 | H52: - | I52: 45486 | J52: 45488 | K52: 45485 | L52: 45485 | M52: -
A53: 534063 | B53: FUTSOL | C53: Futuristic Solutions Ltd | D53: 45478 | E53: Final Dividend | F53: 1 | G53: =IF(ISNUMBER(SEARCH("BONUS", E53)), VALUE(LEFT(F53, FIND(":", F53)-1)) / VALUE(MID(F53, FIND(":", F53)+1, 10)), 0) -> 0 | H53: 45479 | I53: - | J53: - | K53: 45478 | L53: 45478 | M53: -
A54: 523019 | B54: BNRSEC | C54: BN Rathi Securities Ltd | D54: 45463 | E54: Interim Dividend | F54: 1.5 | G54: =IF(ISNUMBER(SEARCH("BONUS", E54)), VALUE(LEFT(F54, FIND(":", F54)-1)) / VALUE(MID(F54, FIND(":", F54)+1, 10)), 0) -> 0 | H54: - | I54: 45464 | J54: 45470 | K54: 45464 | L54: 45464 | M54: -
A55: 500337 | B55: PRIMESECU | C55: Prime Securities Ltd | D55: 45463 | E55: Final Dividend | F55: 1 | G55: =IF(ISNUMBER(SEARCH("BONUS", E55)), VALUE(LEFT(F55, FIND(":", F55)-1)) / VALUE(MID(F55, FIND(":", F55)+1, 10)), 0) -> 0 | H55: - | I55: 45464 | J55: 45470 | K55: 45464 | L55: 45464 | M55: -
A56: 539435 | B56: RFSL | C56: Richfield Financial Services Ltd | D56: 45450 | E56: Interim Dividend | F56: 0.8 | G56: =IF(ISNUMBER(SEARCH("BONUS", E56)), VALUE(LEFT(F56, FIND(":", F56)-1)) / VALUE(MID(F56, FIND(":", F56)+1, 10)), 0) -> 0 | H56: 45450 | I56: - | J56: - | K56: 45450 | L56: 45450 | M56: -
A57: 540097 | B57: GAMCO | C57: Gamco Ltd | D57: 45387 | E57: Interim Dividend | F57: 1 | G57: =IF(ISNUMBER(SEARCH("BONUS", E57)), VALUE(LEFT(F57, FIND(":", F57)-1)) / VALUE(MID(F57, FIND(":", F57)+1, 10)), 0) -> 0 | H57: 45387 | I57: - | J57: - | K57: 45387 | L57: 45387 | M57: -
A58: 531688 | B58: PRITHVIEXCH | C58: Prithvi Exchange (India) Ltd | D58: 45379 | E58: Interim Dividend | F58: 2 | G58: =IF(ISNUMBER(SEARCH("BONUS", E58)), VALUE(LEFT(F58, FIND(":", F58)-1)) / VALUE(MID(F58, FIND(":", F58)+1, 10)), 0) -> 0 | H58: 45380 | I58: - | J58: - | K58: 45378 | L58: 45378 | M58: -
A59: 532810 | B59: PFC | C59: Power Finance Corporation Ltd | D59: 45530 | E59: Bonus issue | F59: 1:6 | G59: =IF(ISNUMBER(SEARCH("BONUS", E59)), VALUE(LEFT(F59, FIND(":", F59)-1)) / VALUE(MID(F59, FIND(":", F59)+1, 10)), 0) -> 0.16666667 | H59: 42611 | I59: - | J59: - | K59: 42604 | L59: 42608 | M59: - | N59: 250
A60: 532955 | B60: RECLTD | C60: REC Ltd | D60: 45563 | E60: Bonus issue | F60: 1:5 | G60: =IF(ISNUMBER(SEARCH("BONUS", E60)), VALUE(LEFT(F60, FIND(":", F60)-1)) / VALUE(MID(F60, FIND(":", F60)+1, 10)), 0) -> 0.2 | H60: 42642 | I60: - | J60: - | K60: 42635 | L60: 42641 | M60: - | N60: 300

Sheet Sheet1
A1: Payout ratio 1:4 | B1: Type CA event
A2: Entity wise divident
A3: D-ref generate

Sheet Pivot_Data
A1: Row Labels | B1: Count of Client ID | E1: Row Labels | F1: Sum of Net Payout | I1: Sum of Net Payout | J1: Sum of TDS Withheld (10%) | K1: Sum of Bonus Shares Received
A2: Processed (Eligible) | B2: 9 | E2: GAMCO | F2: 36135 | I2: 36135 | J2: 4015 | K2: 0
A3: Grand Total | B3: 9 | E3: Grand Total | F3: 36135
