Workbook
Name Slicer_Client_Name: #N/A
Name Slicer_Currency: #N/A
Name Slicer_Validation_Status: #N/A

Sheet FO_Capture
A1: Trade ID | B1: ISIN | C1: Client Code | D1: Qty | E1: Price
A2: TRD00001 | B2: INE006A01070 | C2: C046 | D2: 480 | E2: 314.57999
A3: TRD00002 | B3: INE004A01022 | C3: C027 | D3: 260 | E3: 266.20999
A4: TRD00003 | B4: INE005A01073 | C4: C034 | D4: 300 | E4: 169.60001
A5: TRD00004 | B5: INE004A01066 | C5: C004 | D5: 490 | E5: 128.5
A6: TRD00005 | B6: INE009A01087 | C6: C026 | D6: 160 | E6: 410.75
A7: TRD00006 | B7: INE009A01019 | C7: C021 | D7: 340 | E7: 198.23
A8: TRD00007 | B8: INE008A01087 | C8: C011 | D8: 480 | E8: 336.88
A9: TRD00008 | B9: INE002A01017 | C9: C048 | D9: 250 | E9: 86.709999
A10: TRD00009 | B10: INE007A01073 | C10: C039 | D10: 270 | E10: 371.79999
A11: TRD00010 | B11: INE005A01023 | C11: C020 | D11: 330 | E11: 30.280001
A12: TRD00011 | B12: INE001A01071 | C12: C027 | D12: 180 | E12: 64.339996
A13: TRD00012 | B13: INE008A01025 | C13: C030 | D13: 270 | E13: 390.26001
... A2001: TRD02000 | B2001: INE009A0105 | C2001: C030 | D2001: 120 | E2001: 360.60001

Sheet Reference_Data
A1: Client Code | B1: Client Name | C1: Currency | D1: SSI Details
A2: C001 | B2: Alpha Partners 1 | C2: JPY | D2: Standard Chartered A/C 277005
A3: C002 | B3: Alpha Global 2 | C3: GBP | D3: JPMorgan A/C 582379
A4: C003 | B4: Alpha Partners 3 | C4: USD | D4: Citi A/C 508769
A5: C004 | B5: Alpha Asset Management 4 | C5: JPY | D5: Deutsche Bank A/C 126543
A6: C005 | B6: Alpha Asset Management 5 | C6: INR | D6: JPMorgan A/C 860462
A7: C006 | B7: Alpha Partners 6 | C7: INR | D7: Standard Chartered A/C 441247
A8: C007 | B8: Alpha Capital 7 | C8: INR | D8: Standard Chartered A/C 682134
A9: C008 | B9: Alpha Asset Management 8 | C9: GBP | D9: HDFC A/C 180445
A10: C009 | B10: Alpha Capital 9 | C10: JPY | D10: Citi A/C 744145
A11: C010 | B11: Alpha Capital 10 | C11: USD | D11: HDFC A/C 543407
A12: C011 | B12: Alpha Capital 11 | C12: USD | D12: JPMorgan A/C 987170
... A51: C050 | B51: Alpha Quant Fund 50 | C51: SGD | D51: Standard Chartered A/C 307017

Sheet MO_Validated_Trades
A1: Trade ID | B1: ISIN | C1: Client Name | D1: Currency | E1: SSI Details | F1: Quantity | G1: Price | H1: Gross Value | I1: Validation Status
A2: =FO_Capture!A2 -> TRD00001 | B2: =FO_Capture!B2 -> INE006A01070 | C2: =IFERROR(VLOOKUP(FO_Capture!C2, Reference_Data!A:D, 2, FALSE), "UNKNOWN") -> Alpha Global 46 | D2: =IFERROR(VLOOKUP(FO_Capture!C2, Reference_Data!A:D, 3, FALSE), "XXX") -> USD | E2: =IFERROR(VLOOKUP(FO_Capture!C2, Reference_Data!A:D, 4, FALSE), "MISSING SSI") -> Citi A/C 700450 | F2: =FO_Capture!D2 -> 480 | G2: =FO_Capture!E2 -> 314.57999 | H2: =F2 * G2 -> 150998.39 | I2: =IF(C2="UNKNOWN", "Fail - Missing Ref Data", IF(OR(F2<=0, G2<=0), "Fail - Invalid Price/Qty", IF(H2>1000000, "Exception - Limit Breach", "Pass - Ready for Confirmation"))) -> Pass - Ready for Confirmation
A3: =FO_Capture!A3 -> TRD00002 | B3: =FO_Capture!B3 -> INE004A01022 | C3: =IFERROR(VLOOKUP(FO_Capture!C3, Reference_Data!A:D, 2, FALSE), "UNKNOWN") -> Alpha Quant Fund 27 | D3: =IFERROR(VLOOKUP(FO_Capture!C3, Reference_Data!A:D, 3, FALSE), "XXX") -> EUR | E3: =IFERROR(VLOOKUP(FO_Capture!C3, Reference_Data!A:D, 4, FALSE), "MISSING SSI") -> Standard Chartered A/C 331839 | F3: =FO_Capture!D3 -> 260 | G3: =FO_Capture!E3 -> 266.20999 | H3: =F3 * G3 -> 69214.598 | I3: =IF(C3="UNKNOWN", "Fail - Missing Ref Data", IF(OR(F3<=0, G3<=0), "Fail - Invalid Price/Qty", IF(H3>1000000, "Exception - Limit Breach", "Pass - Ready for Confirmation"))) -> Pass - Ready for Confirmation
A4: =FO_Capture!A4 -> TRD00003 | B4: =FO_Capture!B4 -> INE005A01073 | C4: =IFERROR(VLOOKUP(FO_Capture!C4, Reference_Data!A:D, 2, FALSE), "UNKNOWN") -> Alpha Quant Fund 34 | D4: =IFERROR(VLOOKUP(FO_Capture!C4, Reference_Data!A:D, 3, FALSE), "XXX") -> JPY | E4: =IFERROR(VLOOKUP(FO_Capture!C4, Reference_Data!A:D, 4, FALSE), "MISSING SSI") -> Citi A/C 837378 | F4: =FO_Capture!D4 -> 300 | G4: =FO_Capture!E4 -> 169.60001 | H4: =F4 * G4 -> 50880.002 | I4: =IF(C4="UNKNOWN", "Fail - Missing Ref Data", IF(OR(F4<=0, G4<=0), "Fail - Invalid Price/Qty", IF(H4>1000000, "Exception - Limit Breach", "Pass - Ready for Confirmation"))) -> Pass - Ready for Confirmation
A5: =FO_Capture!A5 -> TRD00004 | B5: =FO_Capture!B5 -> INE004A01066 | C5: =IFERROR(VLOOKUP(FO_Capture!C5, Reference_Data!A:D, 2, FALSE), "UNKNOWN") -> Alpha Asset Management 4 | D5: =IFERROR(VLOOKUP(FO_Capture!C5, Reference_Data!A:D, 3, FALSE), "XXX") -> JPY | E5: =IFERROR(VLOOKUP(FO_Capture!C5, Reference_Data!A:D, 4, FALSE), "MISSING SSI") -> Deutsche Bank A/C 126543 | F5: =FO_Capture!D5 -> 490 | G5: =FO_Capture!E5 -> 128.5 | H5: =F5 * G5 -> 62965 | I5: =IF(C5="UNKNOWN", "Fail - Missing Ref Data", IF(OR(F5<=0, G5<=0), "Fail - Invalid Price/Qty", IF(H5>1000000, "Exception - Limit Breach", "Pass - Ready for Confirmation"))) -> Pass - Ready for Confirmation
A6: =FO_Capture!A6 -> TRD00005 | B6: =FO_Capture!B6 -> INE009A01087 | C6: =IFERROR(VLOOKUP(FO_Capture!C6, Reference_Data!A:D, 2, FALSE), "UNKNOWN") -> Alpha Partners 26 | D6: =IFERROR(VLOOKUP(FO_Capture!C6, Reference_Data!A:D, 3, FALSE), "XXX") -> USD | E6: =IFERROR(VLOOKUP(FO_Capture!C6, Reference_Data!A:D, 4, FALSE), "MISSING SSI") -> HSBC A/C 867781 | F6: =FO_Capture!D6 -> 160 | G6: =FO_Capture!E6 -> 410.75 | H6: =F6 * G6 -> 65720 | I6: =IF(C6="UNKNOWN", "Fail - Missing Ref Data", IF(OR(F6<=0, G6<=0), "Fail - Invalid Price/Qty", IF(H6>1000000, "Exception - Limit Breach", "Pass - Ready for Confirmation"))) -> Pass - Ready for Confirmation
A7: =FO_Capture!A7 -> TRD00006 | B7: =FO_Capture!B7 -> INE009A01019 | C7: =IFERROR(VLOOKUP(FO_Capture!C7, Reference_Data!A:D, 2, FALSE), "UNKNOWN") -> Alpha Holdings 21 | D7: =IFERROR(VLOOKUP(FO_Capture!C7, Reference_Data!A:D, 3, FALSE), "XXX") -> SGD | E7: =IFERROR(VLOOKUP(FO_Capture!C7, Reference_Data!A:D, 4, FALSE), "MISSING SSI") -> HSBC A/C 562956 | F7: =FO_Capture!D7 -> 340 | G7: =FO_Capture!E7 -> 198.23 | H7: =F7 * G7 -> 67398.199 | I7: =IF(C7="UNKNOWN", "Fail - Missing Ref Data", IF(OR(F7<=0, G7<=0), "Fail - Invalid Price/Qty", IF(H7>1000000, "Exception - Limit Breach", "Pass - Ready for Confirmation"))) -> Pass - Ready for Confirmation
A8: =FO_Capture!A8 -> TRD00007 | B8: =FO_Capture!B8 -> INE008A01087 | C8: =IFERROR(VLOOKUP(FO_Capture!C8, Reference_Data!A:D, 2, FALSE), "UNKNOWN") -> Alpha Capital 11 | D8: =IFERROR(VLOOKUP(FO_Capture!C8, Reference_Data!A:D, 3, FALSE), "XXX") -> USD | E8: =IFERROR(VLOOKUP(FO_Capture!C8, Reference_Data!A:D, 4, FALSE), "MISSING SSI") -> JPMorgan A/C 987170 | F8: =FO_Capture!D8 -> 480 | G8: =FO_Capture!E8 -> 336.88 | H8: =F8 * G8 -> 161702.4 | I8: =IF(C8="UNKNOWN", "Fail - Missing Ref Data", IF(OR(F8<=0, G8<=0), "Fail - Invalid Price/Qty", IF(H8>1000000, "Exception - Limit Breach", "Pass - Ready for Confirmation"))) -> Pass - Ready for Confirmation
A9: =FO_Capture!A9 -> TRD00008 | B9: =FO_Capture!B9 -> INE002A01017 | C9: =IFERROR(VLOOKUP(FO_Capture!C9, Reference_Data!A:D, 2, FALSE), "UNKNOWN") -> Alpha Partners 48 | D9: =IFERROR(VLOOKUP(FO_Capture!C9, Reference_Data!A:D, 3, FALSE), "XXX") -> SGD | E9: =IFERROR(VLOOKUP(FO_Capture!C9, Reference_Data!A:D, 4, FALSE), "MISSING SSI") -> JPMorgan A/C 391364 | F9: =FO_Capture!D9 -> 250 | G9: =FO_Capture!E9 -> 86.709999 | H9: =F9 * G9 -> 21677.5 | I9: =IF(C9="UNKNOWN", "Fail - Missing Ref Data", IF(OR(F9<=0, G9<=0), "Fail - Invalid Price/Qty", IF(H9>1000000, "Exception - Limit Breach", "Pass - Ready for Confirmation"))) -> Pass - Ready for Confirmation
A10: =FO_Capture!A10 -> TRD00009 | B10: =FO_Capture!B10 -> INE007A01073 | C10: =IFERROR(VLOOKUP(FO_Capture!C10, Reference_Data!A:D, 2, FALSE), "UNKNOWN") -> Alpha Global 39 | D10: =IFERROR(VLOOKUP(FO_Capture!C10, Reference_Data!A:D, 3, FALSE), "XXX") -> SGD | E10: =IFERROR(VLOOKUP(FO_Capture!C10, Reference_Data!A:D, 4, FALSE), "MISSING SSI") -> Deutsche Bank A/C 917029 | F10: =FO_Capture!D10 -> 270 | G10: =FO_Capture!E10 -> 371.79999 | H10: =F10 * G10 -> 100386 | I10: =IF(C10="UNKNOWN", "Fail - Missing Ref Data", IF(OR(F10<=0, G10<=0), "Fail - Invalid Price/Qty", IF(H10>1000000, "Exception - Limit Breach", "Pass - Ready for Confirmation"))) -> Pass - Ready for Confirmation
A11: =FO_Capture!A11 -> TRD00010 | B11: =FO_Capture!B11 -> INE005A01023 | C11: =IFERROR(VLOOKUP(FO_Capture!C11, Reference_Data!A:D, 2, FALSE), "UNKNOWN") -> Alpha Global 20 | D11: =IFERROR(VLOOKUP(FO_Capture!C11, Reference_Data!A:D, 3, FALSE), "XXX") -> JPY | E11: =IFERROR(VLOOKUP(FO_Capture!C11, Reference_Data!A:D, 4, FALSE), "MISSING SSI") -> Barclays A/C 560891 | F11: =FO_Capture!D11 -> 330 | G11: =FO_Capture!E11 -> 30.280001 | H11: =F11 * G11 -> 9992.4002 | I11: =IF(C11="UNKNOWN", "Fail - Missing Ref Data", IF(OR(F11<=0, G11<=0), "Fail - Invalid Price/Qty", IF(H11>1000000, "Exception - Limit Breach", "Pass - Ready for Confirmation"))) -> Pass - Ready for Confirmation
A12: =FO_Capture!A12 -> TRD00011 | B12: =FO_Capture!B12 -> INE001A01071 | C12: =IFERROR(VLOOKUP(FO_Capture!C12, Reference_Data!A:D, 2, FALSE), "UNKNOWN") -> Alpha Quant Fund 27 | D12: =IFERROR(VLOOKUP(FO_Capture!C12, Reference_Data!A:D, 3, FALSE), "XXX") -> EUR | E12: =IFERROR(VLOOKUP(FO_Capture!C12, Reference_Data!A:D, 4, FALSE), "MISSING SSI") -> Standard Chartered A/C 331839 | F12: =FO_Capture!D12 -> 180 | G12: =FO_Capture!E12 -> 64.339996 | H12: =F12 * G12 -> 11581.199 | I12: =IF(C12="UNKNOWN", "Fail - Missing Ref Data", IF(OR(F12<=0, G12<=0), "Fail - Invalid Price/Qty", IF(H12>1000000, "Exception - Limit Breach", "Pass - Ready for Confirmation"))) -> Pass - Ready for Confirmation
A13: =FO_Capture!A13 -> TRD00012 | B13: =FO_Capture!B13 -> INE008A01025 | C13: =IFERROR(VLOOKUP(FO_Capture!C13, Reference_Data!A:D, 2, FALSE), "UNKNOWN") -> Alpha Global 30 | D13: =IFERROR(VLOOKUP(FO_Capture!C13, Reference_Data!A:D, 3, FALSE), "XXX") -> JPY | E13: =IFERROR(VLOOKUP(FO_Capture!C13, Reference_Data!A:D, 4, FALSE), "MISSING SSI") -> Deutsche Bank A/C 917262 | F13: =FO_Capture!D13 -> 270 | G13: =FO_Capture!E13 -> 390.26001 | H13: =F13 * G13 -> 105370.2 | I13: =IF(C13="UNKNOWN", "Fail - Missing Ref Data", IF(OR(F13<=0, G13<=0), "Fail - Invalid Price/Qty", IF(H13>1000000, "Exception - Limit Breach", "Pass - Ready for Confirmation"))) -> Pass - Ready for Confirmation
... A2001: =FO_Capture!A2001 -> TRD02000 | B2001: =FO_Capture!B2001 -> INE009A0105 | C2001: =IFERROR(VLOOKUP(FO_Capture!C2001, Reference_Data!A:D, 2, FALSE), "UNKNOWN") -> Alpha Global 30 | D2001: =IFERROR(VLOOKUP(FO_Capture!C2001, Reference_Data!A:D, 3, FALSE), "XXX") -> JPY | E2001: =IFERROR(VLOOKUP(FO_Capture!C2001, Reference_Data!A:D, 4, FALSE), "MISSING SSI") -> Deutsche Bank A/C 917262 | F2001: =FO_Capture!D2001 -> 120 | G2001: =FO_Capture!E2001 -> 360.60001 | H2001: =F2001 * G2001 -> 43272.001 | I2001: =IF(C2001="UNKNOWN", "Fail - Missing Ref Data", IF(OR(F2001<=0, G2001<=0), "Fail - Invalid Price/Qty", IF(H2001>1000000, "Exception - Limit Breach", "Pass - Ready for Confirmation"))) -> Pass - Ready for Confirmation

Sheet Pivot Data
A1: Row Labels | B1: Count of Trade ID | D1: Row Labels | E1: Sum of Gross Value
A2: Exception - Limit Breach | B2: 33 | D2: EUR | E2: 46841771
A3: Fail - Invalid Price/Qty | B3: 15 | D3: GBP | E3: 44805633
A4: Fail - Missing Ref Data | B4: 21 | D4: INR | E4: 81223371
A5: Pass - Ready for Confirmation | B5: 1931 | D5: JPY | E5: 68601144
A6: (blank) | D6: SGD | E6: 48592594
A7: Grand Total | B7: 2000 | D7: USD | E7: 64895583
D8: XXX | E8: 1195712.4
D9: (blank)
D10: Grand Total | E10: 3.5615581e+08

Sheet TLC_Dashboard
A1: Middle Office TLC & Exception Dashboard
